modAL/__init__.py
modAL/acquisition.py
modAL/batch.py
modAL/cluster.py
modAL/density.py
modAL/disagreement.py
modAL/dropout.py
modAL/expected_error.py
modAL/multilabel.py
modAL/uncertainty.py
modAL/models/__init__.py
modAL/models/base.py
modAL/models/learners.py
modAL/utils/__init__.py
modAL/utils/combination.py
modAL/utils/data.py
modAL/utils/selection.py
modAL/utils/validation.py
modAL_python-0.4.2.1.dist-info/LICENSE
modAL_python-0.4.2.1.dist-info/METADATA
modAL_python-0.4.2.1.dist-info/WHEEL
modAL_python-0.4.2.1.dist-info/top_level.txt
modAL_python-0.4.2.1.dist-info/RECORD
