Metadata-Version: 2.1
Name: modAL-python
Version: 0.4.2.1
Summary: A modular active learning framework for Python3
Home-page: https://modAL-python.github.io/
Author: Tivadar Danka
Author-email: 85a5187a@opayq.com
License: MIT
Classifier: Development Status :: 4 - Beta
License-File: LICENSE
